README.md
setup.py
sp_api_lib/__init__.py
sp_api_lib/sp_api_lib.py
sp_api_lib.egg-info/PKG-INFO
sp_api_lib.egg-info/SOURCES.txt
sp_api_lib.egg-info/dependency_links.txt
sp_api_lib.egg-info/top_level.txt