Metadata-Version: 2.1
Name: sp-api-lib
Version: 1.0.0
Summary: SP-API Python Library
Author: Greenroomy
Author-email: greenroom1973@gmail.com
